Workbook

Sheet Сводка
A1: Сводка по активному сценарию (меняется переключателем на листе «Допущения»)
A3: Выручка за горизонт | B3: =SUM('Прогноз'!E2:E37)
A4: Денежный поток за горизонт | B4: =SUM('Прогноз'!K2:K37)
A5: NPV | B5: =SUM('Прогноз'!M2:M37)
A6: Макс. потребность в финансировании | B6: =-MIN(0,MIN('Прогноз'!L2:L37))
A7: LTV | B7: ='Допущения'!$F$10*(1-'Допущения'!$F$13)/'Допущения'!$F$11
A8: LTV / CAC | B8: =B7/'Допущения'!$F$12
A11: Сравнение трёх сценариев (рассчитано движком; валюта RUB)
A12: Показатель | B12: Пессимистичный | C12: Базовый | D12: Оптимистичный
A13: NPV | B13: -1.5206118e+08 | C13: -1.1953864e+08 | D13: -38341327
A14: Макс. потребность в финансировании | B14: 2.2646295e+08 | C14: 1.6310047e+08 | D14: 57459210
A15: Месяц окупаемости | B15: > 36 | C15: > 36 | D15: > 36
A16: LTV / CAC | B16: 1.13 | C16: 15.96 | D16: 94.87
A17: Выручка, год 1 | B17: 0 | C17: 506956.69 | D17: 3110494.4
A18: Выручка, год 2 | B18: 1062850.1 | C18: 10598997 | D18: 33057598
A19: Выручка, год 3 | B19: 4382437 | C19: 27604870 | D19: 82422939

Sheet Допущения
A1: Активный сценарий (1 — пессим., 2 — базовый, 3 — оптим.) | B1: 2
A3: Ключ | B3: Драйвер | C3: Пессимистичный | D3: Базовый | E3: Оптимистичный | F3: Активный | G3: Ед. | H3: Источник / логика | I3: Доказательность
A4: launch_delay_months | B4: Срок до запуска | C4: 15 | D4: 9 | E4: 7 | F4: =CHOOSE($B$1,C4,D4,E4) | G4: мес | H4: До первой платной выручки. База: MVP М3, пилоты М4–М5, решение М6–М7 (02_po), запись в реестре М7–М9 (02_certification §4, §6.3) → выручка с М10. Пессим.: MVP 4,5 мес (PO), отказ в реестре и повторная подача +3–5 мес (сертификация), BA: деньги через 9–12 мес после MVP, сезонность IV кв. Оптим.: клиент без требования реестра, договор М6–М7 (PO) | I4: Вывод
A5: dev_investment | B5: Инвестиции в разработку до запуска | C5: 58000000 | D5: 30000000 | E5: 17400000 | F5: =CHOOSE($B$1,C5,D5,E5) | G5: RUB | H5: Вся команда до первой выручки × полная стоимость чел.-мес. (0,48 / 0,60 / 0,42 млн ₽: оклад + взносы IT-аккредитации 15%/7,6% по 02_legal §3.8 + 20% накладных). База: этап 0 1,5 + MVP 13,5 + пилоты 18 + v1/реестр 22,5 ч-мес (02_po дорожная карта) = 55,5 × 0,48 + продавец с М5 2,4 млн + инфраструктура 0,9 млн | I5: Вывод
A6: compliance_one_time | B6: Разовые затраты на право и сертификацию | C6: 11200000 | D6: 7200000 | E6: 3700000 | F6: =CHOOSE($B$1,C6,D6,E6) | G6: RUB | H6: Юрист on-prem+облако 1,13–2,9 млн (02_legal §6) + сертификация базовый сценарий 2,8–8,3 млн (02_certification §6.2) без ФСТЭК, минус дубль G0 0,2–0,5 млн. База — середины, пессим. — верх + повторная подача в реестр 0,5 млн, оптим. — низ | I6: Гипотеза
A7: compliance_annual | B7: Ежегодные затраты на поддержку статусов и комплаенс | C7: 11300000 | D7: 7500000 | E7: 4650000 | F7: =CHOOSE($B$1,C7,D7,E7) | G7: RUB/год | H7: Юрист 0,85–2,6 млн/год (02_legal §6) + сертификация 3,8–7,9 млн/год, из них AppSec/SDL 3–6 (02_certification §6.2). Пессим. + страхование киберрисков 0,8 млн (02_legal) | I7: Гипотеза
A8: new_customers_first_month | B8: Новые клиенты в первый месяц продаж | C8: 0.2 | D8: 0.35 | E8: 0.5 | F8: =CHOOSE($B$1,C8,D8,E8) | G8: шт | H8: 3 пилота × конверсия пилот→договор 40% (02_ba, диапазон 25–60%) ≈ 1,2 договора за первые 3 мес; мощность команды-новичка 4–6 сделок/год (02_ba). Пессим.: 2 пилота × 25%; оптим.: 3–4 пилота × 60% | I8: Гипотеза
A9: new_customers_growth | B9: Рост числа новых клиентов | C9: 0.02 | D9: 0.03 | E9: 0.035 | F9: =CHOOSE($B$1,C9,D9,E9) | G9: доля/мес | H9: Калибровка на SOM 02_ba: база ≈ 13 активных клиентов и ≈ 37 млн ₽ ARR к М36 (SOM 12 клиентов / 36 млн); оптим. ≈ 23 (≤ 28 = SAM 277 × 40% × 25%); пессим. ≈ 4 (нижняя граница SOM) | I9: Вывод
A10: price_per_month | B10: ARPU (выручка на активного клиента) | C10: 119000 | D10: 238000 | E10: 398000 | F10: =CHOOSE($B$1,C10,D10,E10) | G10: RUB/мес | H10: Чек 02_ba 1,5 / 3,0 / 5,0 млн ₽/год; 75% лицензия из реестра (НДС 0%, пп.26 п.2 ст.149 НК) + 25% поддержка (НДС 22%) по 02_legal §3.5 → выручка без НДС 1,43 / 2,87 / 4,78 млн ₽/год ÷ 12 | I10: Гипотеза
A11: monthly_churn | B11: Месячный отток | C11: 0.0237 | D11: 0.0087 | E11: 0.0043 | F11: =CHOOSE($B$1,C11,D11,E11) | G11: доля/мес | H11: Годовой logo churn 02_ba 10% (5–20%) → 1−0,9^(1/12). Пессим. 25%/год — коммодитизация (бюджеты бесплатны в LiteLLM, стандарт российских шлюзов, 02_ba/02_po R8); оптим. 5%/год (низкий отток инфраструктурных вендоров, Arenadata в 02_ba) | I11: Гипотеза
A12: cac | B12: CAC (стоимость привлечения клиента) | C12: 2000000 | D12: 1200000 | E12: 800000 | F12: =CHOOSE($B$1,C12,D12,E12) | G12: RUB | H12: Инкрементальный CAC (фикс продавца и пресейла — в постоянных затратах): пилотные стенды/выезды 0,12 млн ÷ конверсия 40% + маркетинг 3 млн/год ÷ 5 сделок + бонус 10% первого года. Полный CAC ≈ 2,9 млн — в коридоре 02_ba 1,5–3 млн | I12: Гипотеза
A13: variable_cost_share | B13: Переменные затраты | C13: 0.55 | D13: 0.3 | E13: 0.18 | F13: =CHOOSE($B$1,C13,D13,E13) | G13: доля выручки | H13: Поддержка on-prem 0,1–0,2 FTE на клиента в год 1 (02_po), в среднем 0,08 FTE × 0,48 млн × 12 ≈ 16% выручки + партнёрская маржа интеграторов ≈ 10% (02_ba: продажи через партнёров) + облако в аттестованном сегменте и инструменты 3–4% (02_certification). Пессим.: 0,1 FTE при чеке 1,43 млн + 10–15% партнёрам | I13: Вывод
A14: fixed_costs_monthly | B14: Постоянные затраты после запуска | C14: 5500000 | D14: 4200000 | E14: 2800000 | F14: =CHOOSE($B$1,C14,D14,E14) | G14: RUB/мес | H14: Команда этапа 3 02_po §9: ядро 4 + backend 1 + внедрение/поддержка 1 + пресейл 0,5 + PO 1 = 7,5 FTE + 1 продавец = 8,5 FTE × 0,48 млн + инфраструктура 0,1 млн. AppSec — в compliance_annual. Пессим. 9 FTE × 0,6; оптим. 6,5 FTE × 0,42 | I14: Вывод
A15: discount_rate_annual | B15: Ставка дисконтирования | C15: 0.3 | D15: 0.25 | E15: 0.2 | F15: =CHOOSE($B$1,C15,D15,E15) | G15: доля/год | H15: Ключевая ставка ЦБ 14% (сентябрь 2026, Интерфакс) + премия за риск нового продукта без подтверждённого спроса 6–16 п.п. | I15: Вывод

Sheet Прогноз
A1: Месяц | B1: До запуска? | C1: Новые клиенты | D1: Активные клиенты | E1: Выручка | F1: Переменные затраты | G1: Маркетинг (CAC) | H1: Постоянные затраты | I1: Комплаенс | J1: Инвестиции | K1: Денежный поток | L1: Накопленный поток | M1: Дисконт. поток
A2: 1 | B2: =A2<=MAX(1,ROUND('Допущения'!$F$4,0)) | C2: =IF(B2,0,'Допущения'!$F$8*(1+'Допущения'!$F$9)^(A2-MAX(1,ROUND('Допущения'!$F$4,0))-1)) | D2: =C2 | E2: =D2*'Допущения'!$F$10 | F2: =E2*'Допущения'!$F$13 | G2: =C2*'Допущения'!$F$12 | H2: =IF(B2,0,'Допущения'!$F$14) | I2: ='Допущения'!$F$7/12 | J2: =IF(B2,('Допущения'!$F$5+'Допущения'!$F$6)/MAX(1,ROUND('Допущения'!$F$4,0)),0) | K2: =E2-F2-G2-H2-I2-J2 | L2: =K2 | M2: =K2/(1+'Допущения'!$F$15)^(A2/12)
A3: 2 | B3: =A3<=MAX(1,ROUND('Допущения'!$F$4,0)) | C3: =IF(B3,0,'Допущения'!$F$8*(1+'Допущения'!$F$9)^(A3-MAX(1,ROUND('Допущения'!$F$4,0))-1)) | D3: =D2*(1-'Допущения'!$F$11)+C3 | E3: =D3*'Допущения'!$F$10 | F3: =E3*'Допущения'!$F$13 | G3: =C3*'Допущения'!$F$12 | H3: =IF(B3,0,'Допущения'!$F$14) | I3: ='Допущения'!$F$7/12 | J3: =IF(B3,('Допущения'!$F$5+'Допущения'!$F$6)/MAX(1,ROUND('Допущения'!$F$4,0)),0) | K3: =E3-F3-G3-H3-I3-J3 | L3: =L2+K3 | M3: =K3/(1+'Допущения'!$F$15)^(A3/12)
A4: 3 | B4: =A4<=MAX(1,ROUND('Допущения'!$F$4,0)) | C4: =IF(B4,0,'Допущения'!$F$8*(1+'Допущения'!$F$9)^(A4-MAX(1,ROUND('Допущения'!$F$4,0))-1)) | D4: =D3*(1-'Допущения'!$F$11)+C4 | E4: =D4*'Допущения'!$F$10 | F4: =E4*'Допущения'!$F$13 | G4: =C4*'Допущения'!$F$12 | H4: =IF(B4,0,'Допущения'!$F$14) | I4: ='Допущения'!$F$7/12 | J4: =IF(B4,('Допущения'!$F$5+'Допущения'!$F$6)/MAX(1,ROUND('Допущения'!$F$4,0)),0) | K4: =E4-F4-G4-H4-I4-J4 | L4: =L3+K4 | M4: =K4/(1+'Допущения'!$F$15)^(A4/12)
A5: 4 | B5: =A5<=MAX(1,ROUND('Допущения'!$F$4,0)) | C5: =IF(B5,0,'Допущения'!$F$8*(1+'Допущения'!$F$9)^(A5-MAX(1,ROUND('Допущения'!$F$4,0))-1)) | D5: =D4*(1-'Допущения'!$F$11)+C5 | E5: =D5*'Допущения'!$F$10 | F5: =E5*'Допущения'!$F$13 | G5: =C5*'Допущения'!$F$12 | H5: =IF(B5,0,'Допущения'!$F$14) | I5: ='Допущения'!$F$7/12 | J5: =IF(B5,('Допущения'!$F$5+'Допущения'!$F$6)/MAX(1,ROUND('Допущения'!$F$4,0)),0) | K5: =E5-F5-G5-H5-I5-J5 | L5: =L4+K5 | M5: =K5/(1+'Допущения'!$F$15)^(A5/12)
A6: 5 | B6: =A6<=MAX(1,ROUND('Допущения'!$F$4,0)) | C6: =IF(B6,0,'Допущения'!$F$8*(1+'Допущения'!$F$9)^(A6-MAX(1,ROUND('Допущения'!$F$4,0))-1)) | D6: =D5*(1-'Допущения'!$F$11)+C6 | E6: =D6*'Допущения'!$F$10 | F6: =E6*'Допущения'!$F$13 | G6: =C6*'Допущения'!$F$12 | H6: =IF(B6,0,'Допущения'!$F$14) | I6: ='Допущения'!$F$7/12 | J6: =IF(B6,('Допущения'!$F$5+'Допущения'!$F$6)/MAX(1,ROUND('Допущения'!$F$4,0)),0) | K6: =E6-F6-G6-H6-I6-J6 | L6: =L5+K6 | M6: =K6/(1+'Допущения'!$F$15)^(A6/12)
A7: 6 | B7: =A7<=MAX(1,ROUND('Допущения'!$F$4,0)) | C7: =IF(B7,0,'Допущения'!$F$8*(1+'Допущения'!$F$9)^(A7-MAX(1,ROUND('Допущения'!$F$4,0))-1)) | D7: =D6*(1-'Допущения'!$F$11)+C7 | E7: =D7*'Допущения'!$F$10 | F7: =E7*'Допущения'!$F$13 | G7: =C7*'Допущения'!$F$12 | H7: =IF(B7,0,'Допущения'!$F$14) | I7: ='Допущения'!$F$7/12 | J7: =IF(B7,('Допущения'!$F$5+'Допущения'!$F$6)/MAX(1,ROUND('Допущения'!$F$4,0)),0) | K7: =E7-F7-G7-H7-I7-J7 | L7: =L6+K7 | M7: =K7/(1+'Допущения'!$F$15)^(A7/12)
A8: 7 | B8: =A8<=MAX(1,ROUND('Допущения'!$F$4,0)) | C8: =IF(B8,0,'Допущения'!$F$8*(1+'Допущения'!$F$9)^(A8-MAX(1,ROUND('Допущения'!$F$4,0))-1)) | D8: =D7*(1-'Допущения'!$F$11)+C8 | E8: =D8*'Допущения'!$F$10 | F8: =E8*'Допущения'!$F$13 | G8: =C8*'Допущения'!$F$12 | H8: =IF(B8,0,'Допущения'!$F$14) | I8: ='Допущения'!$F$7/12 | J8: =IF(B8,('Допущения'!$F$5+'Допущения'!$F$6)/MAX(1,ROUND('Допущения'!$F$4,0)),0) | K8: =E8-F8-G8-H8-I8-J8 | L8: =L7+K8 | M8: =K8/(1+'Допущения'!$F$15)^(A8/12)
A9: 8 | B9: =A9<=MAX(1,ROUND('Допущения'!$F$4,0)) | C9: =IF(B9,0,'Допущения'!$F$8*(1+'Допущения'!$F$9)^(A9-MAX(1,ROUND('Допущения'!$F$4,0))-1)) | D9: =D8*(1-'Допущения'!$F$11)+C9 | E9: =D9*'Допущения'!$F$10 | F9: =E9*'Допущения'!$F$13 | G9: =C9*'Допущения'!$F$12 | H9: =IF(B9,0,'Допущения'!$F$14) | I9: ='Допущения'!$F$7/12 | J9: =IF(B9,('Допущения'!$F$5+'Допущения'!$F$6)/MAX(1,ROUND('Допущения'!$F$4,0)),0) | K9: =E9-F9-G9-H9-I9-J9 | L9: =L8+K9 | M9: =K9/(1+'Допущения'!$F$15)^(A9/12)
A10: 9 | B10: =A10<=MAX(1,ROUND('Допущения'!$F$4,0)) | C10: =IF(B10,0,'Допущения'!$F$8*(1+'Допущения'!$F$9)^(A10-MAX(1,ROUND('Допущения'!$F$4,0))-1)) | D10: =D9*(1-'Допущения'!$F$11)+C10 | E10: =D10*'Допущения'!$F$10 | F10: =E10*'Допущения'!$F$13 | G10: =C10*'Допущения'!$F$12 | H10: =IF(B10,0,'Допущения'!$F$14) | I10: ='Допущения'!$F$7/12 | J10: =IF(B10,('Допущения'!$F$5+'Допущения'!$F$6)/MAX(1,ROUND('Допущения'!$F$4,0)),0) | K10: =E10-F10-G10-H10-I10-J10 | L10: =L9+K10 | M10: =K10/(1+'Допущения'!$F$15)^(A10/12)
A11: 10 | B11: =A11<=MAX(1,ROUND('Допущения'!$F$4,0)) | C11: =IF(B11,0,'Допущения'!$F$8*(1+'Допущения'!$F$9)^(A11-MAX(1,ROUND('Допущения'!$F$4,0))-1)) | D11: =D10*(1-'Допущения'!$F$11)+C11 | E11: =D11*'Допущения'!$F$10 | F11: =E11*'Допущения'!$F$13 | G11: =C11*'Допущения'!$F$12 | H11: =IF(B11,0,'Допущения'!$F$14) | I11: ='Допущения'!$F$7/12 | J11: =IF(B11,('Допущения'!$F$5+'Допущения'!$F$6)/MAX(1,ROUND('Допущения'!$F$4,0)),0) | K11: =E11-F11-G11-H11-I11-J11 | L11: =L10+K11 | M11: =K11/(1+'Допущения'!$F$15)^(A11/12)
A12: 11 | B12: =A12<=MAX(1,ROUND('Допущения'!$F$4,0)) | C12: =IF(B12,0,'Допущения'!$F$8*(1+'Допущения'!$F$9)^(A12-MAX(1,ROUND('Допущения'!$F$4,0))-1)) | D12: =D11*(1-'Допущения'!$F$11)+C12 | E12: =D12*'Допущения'!$F$10 | F12: =E12*'Допущения'!$F$13 | G12: =C12*'Допущения'!$F$12 | H12: =IF(B12,0,'Допущения'!$F$14) | I12: ='Допущения'!$F$7/12 | J12: =IF(B12,('Допущения'!$F$5+'Допущения'!$F$6)/MAX(1,ROUND('Допущения'!$F$4,0)),0) | K12: =E12-F12-G12-H12-I12-J12 | L12: =L11+K12 | M12: =K12/(1+'Допущения'!$F$15)^(A12/12)
A13: 12 | B13: =A13<=MAX(1,ROUND('Допущения'!$F$4,0)) | C13: =IF(B13,0,'Допущения'!$F$8*(1+'Допущения'!$F$9)^(A13-MAX(1,ROUND('Допущения'!$F$4,0))-1)) | D13: =D12*(1-'Допущения'!$F$11)+C13 | E13: =D13*'Допущения'!$F$10 | F13: =E13*'Допущения'!$F$13 | G13: =C13*'Допущения'!$F$12 | H13: =IF(B13,0,'Допущения'!$F$14) | I13: ='Допущения'!$F$7/12 | J13: =IF(B13,('Допущения'!$F$5+'Допущения'!$F$6)/MAX(1,ROUND('Допущения'!$F$4,0)),0) | K13: =E13-F13-G13-H13-I13-J13 | L13: =L12+K13 | M13: =K13/(1+'Допущения'!$F$15)^(A13/12)
A14: 13 | B14: =A14<=MAX(1,ROUND('Допущения'!$F$4,0)) | C14: =IF(B14,0,'Допущения'!$F$8*(1+'Допущения'!$F$9)^(A14-MAX(1,ROUND('Допущения'!$F$4,0))-1)) | D14: =D13*(1-'Допущения'!$F$11)+C14 | E14: =D14*'Допущения'!$F$10 | F14: =E14*'Допущения'!$F$13 | G14: =C14*'Допущения'!$F$12 | H14: =IF(B14,0,'Допущения'!$F$14) | I14: ='Допущения'!$F$7/12 | J14: =IF(B14,('Допущения'!$F$5+'Допущения'!$F$6)/MAX(1,ROUND('Допущения'!$F$4,0)),0) | K14: =E14-F14-G14-H14-I14-J14 | L14: =L13+K14 | M14: =K14/(1+'Допущения'!$F$15)^(A14/12)
... A37: 36 | B37: =A37<=MAX(1,ROUND('Допущения'!$F$4,0)) | C37: =IF(B37,0,'Допущения'!$F$8*(1+'Допущения'!$F$9)^(A37-MAX(1,ROUND('Допущения'!$F$4,0))-1)) | D37: =D36*(1-'Допущения'!$F$11)+C37 | E37: =D37*'Допущения'!$F$10 | F37: =E37*'Допущения'!$F$13 | G37: =C37*'Допущения'!$F$12 | H37: =IF(B37,0,'Допущения'!$F$14) | I37: ='Допущения'!$F$7/12 | J37: =IF(B37,('Допущения'!$F$5+'Допущения'!$F$6)/MAX(1,ROUND('Допущения'!$F$4,0)),0) | K37: =E37-F37-G37-H37-I37-J37 | L37: =L36+K37 | M37: =K37/(1+'Допущения'!$F$15)^(A37/12)
